veri.py
pyveri-0.1.0.dist-info/METADATA
pyveri-0.1.0.dist-info/WHEEL
pyveri-0.1.0.dist-info/top_level.txt
pyveri-0.1.0.dist-info/RECORD
