Metadata-Version: 2.4
Name: pyveri
Version: 0.1.0
Summary: ctypes wrapper for VERIlator models
Author-email: nzturn <nzturn@gmail.com>
Keywords: fpga
Classifier: Development Status :: 3 - Alpha
Classifier: Intended Audience :: Developers
Classifier: Programming Language :: Python :: 3
Requires-Python: >=3.8
